LICENSE
README.md
setup.py
equitorch/__init__.py
equitorch/typing.py
equitorch.egg-info/PKG-INFO
equitorch.egg-info/SOURCES.txt
equitorch.egg-info/dependency_links.txt
equitorch.egg-info/requires.txt
equitorch.egg-info/top_level.txt
equitorch/math/Jd.pt
equitorch/math/__init__.py
equitorch/math/sht.py
equitorch/math/so3.py
equitorch/nn/__init__.py
equitorch/nn/activation.py
equitorch/nn/angular_basis.py
equitorch/nn/attention.py
equitorch/nn/cutoff.py
equitorch/nn/linear.py
equitorch/nn/normalization.py
equitorch/nn/other.py
equitorch/nn/radial_basis.py
equitorch/nn/spherical_basis.py
equitorch/nn/tensor_product copy.py
equitorch/nn/tensor_product.py
equitorch/transforms/__init__.py
equitorch/utils/__init__.py
equitorch/utils/clebsch_gordan.py
equitorch/utils/geometries.py
equitorch/utils/hooks.py
equitorch/utils/indices.py
equitorch/utils/weights.py
tests/test_conv.py
tests/test_eqtensor.py
tests/test_rotation.py
tests/test_so2.py
tests/test_so3.py
tests/test_so3_.py
tests/test_wd.py
tests/testtp.py